{
  "project_info": {
    "project_number": "114704067467",
    "project_id": "studentcard-5714c",
    "storage_bucket": "studentcard-5714c.appspot.com"
  },
  "client": [
    {
      "client_info": {
        "mobilesdk_app_id": "1:114704067467:android:120b97621089183daa9d8e",
        "android_client_info": {
          "package_name": "com.spyros.studentcard"
        }
      },
      "oauth_client": [],
      "api_key": [
        {
          "current_key": "AIzaSyA5jkvPhU4YvQ3wku9pvxAQrStWFe1lAQo"
        }
      ],
      "services": {
        "appinvite_service": {
          "other_platform_oauth_client": []
        }
      }
    }
  ],
  "configuration_version": "1"
}